[
  {
    "id": "tutorial",
    "title": "Getting Started",
    "description": "A guided introduction to Knogra — nodes, scenes, AI assistant, and more. Start here.",
    "tags": ["tutorial", "intro"],
    "nodeCount": 26,
    "badge": "Tutorial",
    "file": "graphs/tutorial.knogra"
  },
  {
    "id": "quantum-mechanics",
    "title": "Quantum mechanics basics",
    "description": "A graph exploring basic concepts of the quantum mechanics.",
    "tags": ["demo", "equations"],
    "nodeCount": 30,
    "file": "graphs/graph-quantum-mechanics-2026-05-22.knogra"
  },
  {
    "id": "agentic-ai",
    "title": "Agentic AI basics",
    "description": "A graph exploring basic concepts of the agentic ai",
    "tags": ["demo", "ai agents"],
    "nodeCount": 30,
    "file": "graphs/graph-agentic-ai-2026-05-22.knogra"
  },
  {
    "id": "graph-internet",
    "title": "Internet and the Web",
    "description": "The internet, mapped end to end — from cables, packets, and IP addresses up through DNS, TCP, HTTP, and the browser rendering this page. 600+ concepts you can drill into, scene by scene.",
    "tags": ["demo"],
    "nodeCount": 629,
    "badge": "New",
    "file": "graphs/graph-internet.knogra"
  },
  {
    "id": "graph-calculus",
    "title": "Calculus, End to End",
    "description": "All of first-year calculus on one map — Functions, Limits, Differentiation, Integration, Differential Equations, Numerical Methods — each node carrying its actual formula. Drill in scene by scene instead of drowning in one flat diagram.",
    "tags": ["demo"],
    "nodeCount": 104,
    "badge": "New",
    "file": "graphs/graph-calculus.knogra"
  }
]
